reapy_boost/ImGui.py
reapy_boost/__init__.py
reapy_boost/__main__.py
reapy_boost/additional_api.py
reapy_boost/errors.py
reapy_boost/py.typed
reapy_boost/reascript_api.py
reapy_boost/.mypy_cache/.gitignore
reapy_boost/.mypy_cache/CACHEDIR.TAG
reapy_boost/.mypy_cache/3.10/@plugins_snapshot.json
reapy_boost/.mypy_cache/3.10/_ast.data.json
reapy_boost/.mypy_cache/3.10/_ast.meta.json
reapy_boost/.mypy_cache/3.10/_codecs.data.json
reapy_boost/.mypy_cache/3.10/_codecs.meta.json
reapy_boost/.mypy_cache/3.10/_collections_abc.data.json
reapy_boost/.mypy_cache/3.10/_collections_abc.meta.json
reapy_boost/.mypy_cache/3.10/_decimal.data.json
reapy_boost/.mypy_cache/3.10/_decimal.meta.json
reapy_boost/.mypy_cache/3.10/_operator.data.json
reapy_boost/.mypy_cache/3.10/_operator.meta.json
reapy_boost/.mypy_cache/3.10/_random.data.json
reapy_boost/.mypy_cache/3.10/_random.meta.json
reapy_boost/.mypy_cache/3.10/_socket.data.json
reapy_boost/.mypy_cache/3.10/_socket.meta.json
reapy_boost/.mypy_cache/3.10/_warnings.data.json
reapy_boost/.mypy_cache/3.10/_warnings.meta.json
reapy_boost/.mypy_cache/3.10/abc.data.json
reapy_boost/.mypy_cache/3.10/abc.meta.json
reapy_boost/.mypy_cache/3.10/array.data.json
reapy_boost/.mypy_cache/3.10/array.meta.json
reapy_boost/.mypy_cache/3.10/builtins.data.json
reapy_boost/.mypy_cache/3.10/builtins.meta.json
reapy_boost/.mypy_cache/3.10/codecs.data.json
reapy_boost/.mypy_cache/3.10/codecs.meta.json
reapy_boost/.mypy_cache/3.10/configparser.data.json
reapy_boost/.mypy_cache/3.10/configparser.meta.json
reapy_boost/.mypy_cache/3.10/contextlib.data.json
reapy_boost/.mypy_cache/3.10/contextlib.meta.json
reapy_boost/.mypy_cache/3.10/decimal.data.json
reapy_boost/.mypy_cache/3.10/decimal.meta.json
reapy_boost/.mypy_cache/3.10/dis.data.json
reapy_boost/.mypy_cache/3.10/dis.meta.json
reapy_boost/.mypy_cache/3.10/enum.data.json
reapy_boost/.mypy_cache/3.10/enum.meta.json
reapy_boost/.mypy_cache/3.10/fractions.data.json
reapy_boost-0.10.201.dist-info/LICENSE.txt
reapy_boost-0.10.201.dist-info/METADATA
reapy_boost-0.10.201.dist-info/WHEEL
reapy_boost-0.10.201.dist-info/top_level.txt
reapy_boost-0.10.201.dist-info/RECORD
