Metadata-Version: 2.1
Name: reapy-boost
Version: 0.10.201
Summary: A pythonic wrapper for REAPER's ReaScript Python API
Author: Roméo Després, forked by Levitanus
Author-email: pianoist@ya.ru
License: MIT
Keywords: REAPER DAW ReaScript API wrapper music audio
Classifier: License :: OSI Approved :: MIT License
Classifier: Programming Language :: Python :: 3
Requires-Python: >=3.7
License-File: LICENSE.txt
Requires-Dist: psutil
